LICENSE
MANIFEST.in
README.rst
setup.cfg
setup.py
./d3nb/__init__.py
d3nb.egg-info/PKG-INFO
d3nb.egg-info/SOURCES.txt
d3nb.egg-info/dependency_links.txt
d3nb.egg-info/requires.txt
d3nb.egg-info/top_level.txt