Metadata-Version: 1.1
Name: d3nb
Version: 0.0.2
Summary: d3js
Home-page: https://github.com/jbn/d3js
Author: John Bjorn Nelson
Author-email: jbn@abreka.com
License: MIT
Keywords: d3js,d3.js,d3
Platform: UNKNOWN
Classifier: Development Status :: 3 - Alpha
Classifier: Framework :: IPython
Classifier: Topic :: Communications
Classifier: Natural Language :: English
Classifier: License :: OSI Approved :: MIT License
Classifier: Operating System :: OS Independent
Classifier: Programming Language :: Python :: 3.5
Classifier: Topic :: Software Development :: Libraries :: Python Modules
